high/__init__.py
one/__init__.py
stahmctestt_your_username-1.5.dist-info/LICENSE
stahmctestt_your_username-1.5.dist-info/METADATA
stahmctestt_your_username-1.5.dist-info/WHEEL
stahmctestt_your_username-1.5.dist-info/top_level.txt
stahmctestt_your_username-1.5.dist-info/RECORD
