Metadata-Version: 2.1
Name: stahmctestt-your-username
Version: 1.5
Summary: A small example package
Home-page: https://github.com/RihuiOu95/HMC.git
Author: Tianhui
Author-email: thuizhou@outlook.com
License: UNKNOWN
Platform: UNKNOWN
Classifier: Programming Language :: Python :: 3
Classifier: License :: OSI Approved :: MIT License
Classifier: Operating System :: OS Independent
